tktelerik/Telerik.WinControls.RadDiagram.dll
tktelerik/Telerik.WinControls.SyntaxEditor.dll
tktelerik/Telerik.WinControls.Themes.Fluent.dll
tktelerik/Telerik.WinControls.Themes.FluentDark.dll
tktelerik/Telerik.WinControls.Themes.Material.dll
tktelerik/Telerik.WinControls.Themes.Windows11.dll
tktelerik/Telerik.WinControls.UI.dll
tktelerik/Telerik.WinControls.dll
tktelerik/__init__.py
tktelerik/__main__.py
tktelerik/base.py
tktelerik/download.py
tktelerik/telerik.demo.1.py
tktelerik/telerik.demo.2.py
tktelerik/telerik.demo.3.py
tktelerik/telerik.demo.4.py
tktelerik/telerik.demo.5.py
tktelerik/telerik.demo.6.py
tktelerik/telerik.demo.7.py
tktelerik/telerik.py
tktelerik-1.0.0.dist-info/METADATA
tktelerik-1.0.0.dist-info/WHEEL
tktelerik-1.0.0.dist-info/top_level.txt
tktelerik-1.0.0.dist-info/RECORD
