Metadata-Version: 2.1
Name: tktelerik
Version: 1.0.0
Summary: tkinter with telerik
Author: XiangQinxi
Author-email: XiangQinxi@outlook.com
Classifier: Programming Language :: Python :: 3
Classifier: License :: OSI Approved :: MIT License
Classifier: Operating System :: OS Independent
Requires: pythonnet
Requires: tqdm
Requires-Python: >=3
